README.md
setup.py
OmniDatabase/__init__.py
OmniDatabase.egg-info/PKG-INFO
OmniDatabase.egg-info/SOURCES.txt
OmniDatabase.egg-info/dependency_links.txt
OmniDatabase.egg-info/not-zip-safe
OmniDatabase.egg-info/requires.txt
OmniDatabase.egg-info/top_level.txt