Metadata-Version: 1.0
Name: OmniDatabase
Version: 0.6
Summary: Generic database metadata and access provider
Home-page: http://github.com/OmniDB/OmniDatabase
Author: William Ivanski
Author-email: william.ivanski@gmail.com
License: MIT
Platform: UNKNOWN
